wwpdb/utils/session/FileUtils.py
wwpdb/utils/session/SessionManager.py
wwpdb/utils/session/UtilDataStore.py
wwpdb/utils/session/WebAppWorkerBase.py
wwpdb/utils/session/WebDownloadUtils.py
wwpdb/utils/session/WebRequest.py
wwpdb/utils/session/WebUploadUtils.py
wwpdb/utils/session/WwPdbWebOb.py
wwpdb/utils/session/__init__.py
wwpdb_utils_session-0.18.1.dist-info/METADATA
wwpdb_utils_session-0.18.1.dist-info/WHEEL
wwpdb_utils_session-0.18.1.dist-info/RECORD
