Metadata-Version: 2.4
Name: wwpdb.utils.session
Version: 0.18.1
Summary: wwPDB session support
Project-URL: Homepage, https://github.com/rcsb/py-wwpdb_utils_session
Author-email: Ezra Peisach <ezra.peisach@rcsb.org>
License-Expression: Apache-2.0
Classifier: Development Status :: 3 - Alpha
Classifier: Intended Audience :: Developers
Classifier: License :: OSI Approved :: Apache Software License
Classifier: Natural Language :: English
Classifier: Programming Language :: Python
Classifier: Programming Language :: Python :: 2.7
Classifier: Programming Language :: Python :: 3
Classifier: Programming Language :: Python :: 3.6
Classifier: Programming Language :: Python :: 3.7
Requires-Python: >=3.6
Requires-Dist: webob
Requires-Dist: wwpdb-io
Requires-Dist: wwpdb-utils-config
